pointz
