Metadata-Version: 1.1
Name: pointz
Version: 0.4
Summary: Prova de Conceito para Passagem de dados de SQL Server para Big Query
Home-page: https://github.com/renzon/pointz
Author: Renzo Nuccitelli
Author-email: renzo.n@gmail.com
License: BSD
Platform: UNKNOWN
Classifier: Development Status :: 3 - Alpha
Classifier: Environment :: Console
Classifier: Intended Audience :: Developers
Classifier: License :: OSI Approved :: BSD License
Classifier: License :: OSI Approved :: GNU Affero General Public License v3 or later (AGPLv3+)
Classifier: Programming Language :: Python
